{
    "market_cap": 0,
    "volume": 2087641688,
    "market_data": {
        "ath": {
            "aed": 17864.35,
            "ars": 487063,
            "aud": 6679.6,
            "bch": 14.614274,
            "bdt": 417162,
            "bhd": 1833.87,
            "bmd": 4863.7,
            "bnb": 34.36095,
            "brl": 26879,
            "btc": 0.14280504,
            "cad": 6092.1,
            "chf": 4454.99,
            "clp": 3978618,
            "cny": 31073,
            "czk": 107636,
            "dkk": 31385,
            "dot": 292.03,
            "eos": 1611,
            "eth": 3.614831,
            "eur": 4220.12,
            "gbp": 3608.74,
            "hkd": 37883,
            "huf": 1537225,
            "idr": 69357389,
            "ils": 15145.94,
            "inr": 361524,
            "jpy": 553701,
            "krw": 5765389,
            "kwd": 1467.45,
            "lkr": 1064265,
            "ltc": 33.01904,
            "mmk": 8891159,
            "mxn": 101865,
            "myr": 20189,
            "ngn": 2004367,
            "nok": 43194,
            "nzd": 6977.84,
            "php": 243570,
            "pkr": 838631,
            "pln": 19598.46,
            "rub": 405508,
            "sar": 18242.07,
            "sek": 43058,
            "sgd": 172382210,
            "thb": 161071,
            "try": 70145,
            "twd": 134961,
            "uah": 129995,
            "usd": 4863.7,
            "vef": 285793463,
            "vnd": 110455597,
            "xag": 210.64,
            "xau": 2.68,
            "xdr": 3448.15,
            "xlm": 20869,
            "xrp": 5417,
            "yfi": 0.29781323,
            "zar": 75749,
            "bits": 142805,
            "link": 3368,
            "sats": 14280504
        },
        "atl": {
            "aed": 1.45e-15,
            "ars": 3.0898e-14,
            "aud": 5.57e-16,
            "bch": 1.0e-18,
            "bdt": 3.3408e-14,
            "bhd": 1.49e-16,
            "bmd": 3.95e-16,
            "bnb": 1.3e-17,
            "brl": 2.252e-15,
            "btc": 0,
            "cad": 5.23e-16,
            "chf": 3.6e-16,
            "clp": 3.05768e-13,
            "cny": 2.648e-15,
            "czk": 9.222e-15,
            "dkk": 2.502e-15,
            "dot": 8.7e-17,
            "eos": 1.47e-16,
            "eth": 1.0e-18,
            "eur": 3.36e-16,
            "gbp": 3.04e-16,
            "hkd": 3.059e-15,
            "huf": 1.23459e-13,
            "idr": 5.805e-12,
            "ils": 1.338e-15,
            "inr": 2.9154e-14,
            "jpy": 4.1129e-14,
            "krw": 4.48041e-13,
            "kwd": 1.21e-16,
            "lkr": 7.2726e-14,
            "ltc": 7.0e-18,
            "mmk": 5.07524e-13,
            "mxn": 8.408e-15,
            "myr": 1.64e-15,
            "ngn": 1.50722e-13,
            "nok": 3.679e-15,
            "nzd": 5.92e-16,
            "php": 1.9091e-14,
            "pkr": 6.3618e-14,
            "pln": 1.554e-15,
            "rub": 3.0946e-14,
            "sar": 1.48e-15,
            "sek": 3.479e-15,
            "sgd": 5.38e-16,
            "thb": 1.2309e-14,
            "try": 3.275e-15,
            "twd": 1.1292e-14,
            "uah": 1.1192e-14,
            "usd": 3.95e-16,
            "vef": 9.8064e-11,
            "vnd": 9.213e-12,
            "xag": 1.6e-17,
            "xau": 0,
            "xdr": 2.79e-16,
            "xlm": 2.878e-15,
            "xrp": 9.03e-16,
            "yfi": 0,
            "zar": 6.46e-15,
            "bits": 16290.27,
            "link": 3.4e-17,
            "sats": 1629027
        },
        "current_prices": {
            "aed": 6496.58,
            "ars": 363828,
            "aud": 2661.88,
            "bch": 14.204269,
            "bdt": 186096,
            "bhd": 667.03,
            "bmd": 1769.02,
            "bnb": 5.468129,
            "brl": 9293.37,
            "btc": 0.06334281,
            "cad": 2431.01,
            "chf": 1627.02,
            "clp": 1435471,
            "cny": 12149.81,
            "czk": 38934,
            "dkk": 12252.75,
            "dot": 290.091,
            "eos": 1494,
            "eth": 1.000433,
            "eur": 1644.19,
            "gbp": 1446.79,
            "hkd": 13886.72,
            "huf": 632994,
            "idr": 26847813,
            "ils": 6359.65,
            "inr": 145689,
            "jpy": 231245,
            "krw": 2293329,
            "kwd": 541.61,
            "lkr": 571959,
            "ltc": 19.345751,
            "mmk": 3718027,
            "mxn": 32655,
            "myr": 7835.88,
            "ngn": 814598,
            "nok": 18557.07,
            "nzd": 2853.29,
            "php": 95996,
            "pkr": 500838,
            "pln": 7708.08,
            "rub": 136709,
            "sar": 6645.28,
            "sek": 18448.53,
            "sgd": 2356.26,
            "thb": 60516,
            "try": 33724,
            "twd": 53667,
            "uah": 65388,
            "usd": 1769.02,
            "vef": 177.13,
            "vnd": 41614235,
            "xag": 76.51,
            "xau": 0.893868,
            "xdr": 1326.65,
            "xlm": 19901,
            "xrp": 4136,
            "yfi": 0.20997363,
            "zar": 32136,
            "bits": 63343,
            "link": 241.467,
            "sats": 6334281
        },
        "price_change_24h_in_currency": {
            "aed": -155.28752657850055,
            "ars": -8878.963354116597,
            "aud": -50.897053277722534,
            "bch": -0.049850288817383515,
            "bdt": -4055.162520558515,
            "bhd": -16.065283923889865,
            "bmd": -42.28485249582263,
            "bnb": -0.018559851218200585,
            "brl": -282.99909551823293,
            "btc": -0.001169589019740666,
            "cad": -55.17054169761832,
            "chf": -31.761392790601576,
            "clp": -27247.953661165433,
            "cny": -203.11168952533626,
            "czk": -560.5017294207064,
            "dkk": -195.3820117293617,
            "dot": 2.496341,
            "eos": -79.20284465545797,
            "eth": 0.00139594,
            "eur": -26.754026870377174,
            "gbp": -28.351734779057324,
            "hkd": -331.70756471191635,
            "huf": -8323.565917626023,
            "idr": -544443.4220545888,
            "ils": -69.69970722490598,
            "inr": -3195.636947530962,
            "jpy": -4921.132181714958,
            "krw": -38155.05377331842,
            "kwd": -12.688809685388378,
            "lkr": -7012.690388711169,
            "ltc": -0.014348476862647177,
            "mmk": -81566.27811831748,
            "mxn": -1060.0289263811464,
            "myr": -166.47074546088606,
            "ngn": -19471.328877274645,
            "nok": -283.4969250309696,
            "nzd": -43.85456339555776,
            "php": -2380.6136874703516,
            "pkr": -10941.699401508318,
            "pln": -119.1296779803879,
            "rub": -949.7271395850985,
            "sar": -159.0393812504435,
            "sek": -259.69025929058625,
            "sgd": -48.741293425226104,
            "thb": -1152.141638595087,
            "try": -772.9485908882561,
            "twd": -1276.1021982602033,
            "uah": -1106.715579051117,
            "usd": -42.28485249582263,
            "vef": -4.233982280406622,
            "vnd": -949631.2042265758,
            "xag": -2.126169850358707,
            "xau": -0.012925431343760565,
            "xdr": -28.91600479970134,
            "xlm": 337.998,
            "xrp": 54.555,
            "yfi": 0.00040206,
            "zar": -660.8204175280407,
            "bits": -1169.5890197406698,
            "link": -0.22638991763454896,
            "sats": -116958.90197406709
        },
        "total_volume": {
            "aed": 7666686650,
            "ars": 429357332969,
            "aud": 3141318289,
            "bch": 16762625,
            "bdt": 219614519481,
            "bhd": 787166175,
            "bmd": 2087641688,
            "bnb": 6453004,
            "brl": 10967216845,
            "btc": 74752,
            "cad": 2868868523,
            "chf": 1920068778,
            "clp": 1694016847870,
            "cny": 14338131879,
            "czk": 45946908003,
            "dkk": 14459620099,
            "dot": 342340101,
            "eos": 1763107818,
            "eth": 1180622,
            "eur": 1940323077,
            "gbp": 1707375667,
            "hkd": 16387882870,
            "huf": 747004124146,
            "idr": 31683420913427,
            "ils": 7505092745,
            "inr": 171928860644,
            "jpy": 272894715606,
            "krw": 2706384336582,
            "kwd": 639156555,
            "lkr": 674975252187,
            "ltc": 22830149,
            "mmk": 4387688010234,
            "mxn": 38536195450,
            "myr": 9247208858,
            "ngn": 961317244571,
            "nok": 21899415588,
            "nzd": 3367201119,
            "php": 113285878296,
            "pkr": 591045411358,
            "pln": 9096397622,
            "rub": 161332434015,
            "sar": 7842171723,
            "sek": 21771324157,
            "sgd": 2780648960,
            "thb": 71415134530,
            "try": 39797757323,
            "twd": 63333203423,
            "uah": 77164837938,
            "usd": 2087641688,
            "vef": 209035562,
            "vnd": 49109450198296,
            "xag": 90288123,
            "xau": 1054864,
            "xdr": 1565593482,
            "xlm": 23485169374,
            "xrp": 4881219614,
            "yfi": 247792,
            "zar": 37924320197,
            "bits": 74751597915,
            "link": 284958169,
            "sats": 7475159791519
        },
        "market_cap": {
            "aed": 0,
            "ars": 0,
            "aud": 0,
            "bch": 0,
            "bdt": 0,
            "bhd": 0,
            "bmd": 0,
            "bnb": 0,
            "brl": 0,
            "btc": 0,
            "cad": 0,
            "chf": 0,
            "clp": 0,
            "cny": 0,
            "czk": 0,
            "dkk": 0,
            "dot": 0,
            "eos": 0,
            "eth": 0,
            "eur": 0,
            "gbp": 0,
            "hkd": 0,
            "huf": 0,
            "idr": 0,
            "ils": 0,
            "inr": 0,
            "jpy": 0,
            "krw": 0,
            "kwd": 0,
            "lkr": 0,
            "ltc": 0,
            "mmk": 0,
            "mxn": 0,
            "myr": 0,
            "ngn": 0,
            "nok": 0,
            "nzd": 0,
            "php": 0,
            "pkr": 0,
            "pln": 0,
            "rub": 0,
            "sar": 0,
            "sek": 0,
            "sgd": 0,
            "thb": 0,
            "try": 0,
            "twd": 0,
            "uah": 0,
            "usd": 0,
            "vef": 0,
            "vnd": 0,
            "xag": 0,
            "xau": 0,
            "xdr": 0,
            "xlm": 0,
            "xrp": 0,
            "yfi": 0,
            "zar": 0,
            "bits": 0,
            "link": 0,
            "sats": 0
        },
        "minted_supply": 55765192
    },
    "images": {
        "thumb": "https://assets.coingecko.com/coins/images/11683/thumb/Balancer.png?1592792958",
        "small": "https://assets.coingecko.com/coins/images/11683/small/Balancer.png?1592792958",
        "large": "https://assets.coingecko.com/coins/images/11683/large/Balancer.png?1592792958"
    },
    "socials": {
        "website": "https://balancer.finance",
        "discord": "https://discord.gg/ARJWaeF",
        "twitter": "Balancer"
    }
}
